odoo10_addon_product_variant_default_code-10.0.1.0.2-py2.7-nspkg.pth
odoo/addons/product_variant_default_code/README.rst
odoo/addons/product_variant_default_code/__init__.py
odoo/addons/product_variant_default_code/__manifest__.py
odoo/addons/product_variant_default_code/data/ir_config_parameter.xml
odoo/addons/product_variant_default_code/demo/attribute_demo.xml
odoo/addons/product_variant_default_code/i18n/ar.po
odoo/addons/product_variant_default_code/i18n/ca.po
odoo/addons/product_variant_default_code/i18n/de.po
odoo/addons/product_variant_default_code/i18n/es.po
odoo/addons/product_variant_default_code/i18n/es_MX.po
odoo/addons/product_variant_default_code/i18n/fi.po
odoo/addons/product_variant_default_code/i18n/fr.po
odoo/addons/product_variant_default_code/i18n/fr_CH.po
odoo/addons/product_variant_default_code/i18n/hr.po
odoo/addons/product_variant_default_code/i18n/hr_HR.po
odoo/addons/product_variant_default_code/i18n/it.po
odoo/addons/product_variant_default_code/i18n/nl_NL.po
odoo/addons/product_variant_default_code/i18n/pt_BR.po
odoo/addons/product_variant_default_code/i18n/ro.po
odoo/addons/product_variant_default_code/i18n/sl.po
odoo/addons/product_variant_default_code/i18n/tr_TR.po
odoo/addons/product_variant_default_code/i18n/vi_VN.po
odoo/addons/product_variant_default_code/i18n/zh_CN.po
odoo/addons/product_variant_default_code/models/__init__.py
odoo/addons/product_variant_default_code/models/config_settings.py
odoo/addons/product_variant_default_code/models/product.py
odoo/addons/product_variant_default_code/security/product_security.xml
odoo/addons/product_variant_default_code/tests/__init__.py
odoo/addons/product_variant_default_code/tests/test_variant_default_code.py
odoo/addons/product_variant_default_code/views/config_settings_view.xml
odoo/addons/product_variant_default_code/views/product_attribute_value_view.xml
odoo/addons/product_variant_default_code/views/product_attribute_view.xml
odoo10_addon_product_variant_default_code-10.0.1.0.2.dist-info/DESCRIPTION.rst
odoo10_addon_product_variant_default_code-10.0.1.0.2.dist-info/METADATA
odoo10_addon_product_variant_default_code-10.0.1.0.2.dist-info/RECORD
odoo10_addon_product_variant_default_code-10.0.1.0.2.dist-info/WHEEL
odoo10_addon_product_variant_default_code-10.0.1.0.2.dist-info/metadata.json
odoo10_addon_product_variant_default_code-10.0.1.0.2.dist-info/namespace_packages.txt
odoo10_addon_product_variant_default_code-10.0.1.0.2.dist-info/top_level.txt
